tgcs_utils/__init__.py
tgcs_utils/create_build_env.py
tgcs_utils/extract_version.py
tgcs_utils/main.py
tgcs_utils/release.py
tgcs_utils-0.1.3.dist-info/METADATA
tgcs_utils-0.1.3.dist-info/WHEEL
tgcs_utils-0.1.3.dist-info/entry_points.txt
tgcs_utils-0.1.3.dist-info/licenses/LICENSE
tgcs_utils-0.1.3.dist-info/RECORD
