Metadata-Version: 2.4
Name: tgcs-utils
Version: 0.1.3
Summary: Python CLI utilities for David's Trail Guide System.
License-File: LICENSE
Requires-Python: >=3.13
Requires-Dist: cappa>=0.27.2
Requires-Dist: requests>=2.32.3
